{
    "Renderer": {
        "FrameResourceList": {
            "Count": 3,
            "Template": null
        },
        "SwapChain": {
            "BackBufferNum": 2,
            "SyncInterval": 1
        }
    },
    "ResourceContext": {
        "RTVDescriptorPool": {
            "DescriptorHeapIndexAllocator": {
                "DescriptorHeapIndexAllocatorCapacity": 10000
            }
        },
        "SRVDescriptorPool": {
            "DescriptorHeapIndexAllocator": {
                "DescriptorHeapIndexAllocatorCapacity": 10000
            }
        },
        "UploadSystem": {
            "CopyCommandAllocatorList": {
                "Count": 4
            }
        }
    }
}